CHANGELOG.rst
LICENSE.txt
MANIFEST.in
README.rst
requirements.txt
requirements_dev.txt
setup.cfg
setup.py
fiware_cloto/__init__.py
fiware_cloto/manage.py
fiware_cloto.egg-info/PKG-INFO
fiware_cloto.egg-info/SOURCES.txt
fiware_cloto.egg-info/dependency_links.txt
fiware_cloto.egg-info/requires.txt
fiware_cloto.egg-info/top_level.txt
fiware_cloto/cloto/__init__.py
fiware_cloto/cloto/constants.py
fiware_cloto/cloto/information.py
fiware_cloto/cloto/models.py
fiware_cloto/cloto/restCloto.py
fiware_cloto/cloto/urls.py
fiware_cloto/cloto/views.py
fiware_cloto/cloto/wsgi.py
fiware_cloto/cloto/manager/AuthorizationManager.py
fiware_cloto/cloto/manager/InfoManager.py
fiware_cloto/cloto/manager/RuleManager.py
fiware_cloto/cloto/manager/__init__.py
fiware_cloto/cloto/utils/__init__.py
fiware_cloto/cloto/utils/log.py
fiware_cloto/cloto_settings/__init__.py
fiware_cloto/cloto_settings/jenkins.py
fiware_cloto/cloto_settings/settings.py
fiware_cloto/cloto_settings/settings_tests.py
fiware_cloto/environments/__init__.py
fiware_cloto/environments/environment.py
fiware_cloto/environments/environmentManager.py
fiware_cloto/environments/environment_controller.py
fiware_cloto/environments/log.py
fiware_cloto/orion_wrapper/__init__.py
fiware_cloto/orion_wrapper/orion_client.py
licenses/circus.txt
licenses/pika.txt
licenses/pyClips.txt
licenses/python-keystoneclient.txt