Metadata-Version: 1.1
Name: fiware-cloto
Version: 2.8.0
Summary: This module is part of FIWARE Policy Manager. It provides a REST API to create rules associated to servers, subscribe servers to Context Broker to get information about their resources consumption and launch actions described in rules when conditions are met.
Home-page: https://github.com/telefonicaid/fiware-cloto
Author: Fernando Lopez Aguilar, Guillermo Jimenez Prieto
Author-email: fernando.lopezaguilar@telefonica.com, e.fiware.tid@telefonica.com
License: Apache 2.0
Download-URL: https://github.com/telefonicaid/fiware-cloto/tarball/v2.8.0
Keywords: fiware,policy,manager,cloud
Platform: UNKNOWN
Classifier: License :: OSI Approved :: Apache Software License
